streamlit_cookies_manager/__init__.py
streamlit_cookies_manager/build/asset-manifest.json
streamlit_cookies_manager/build/index.html
streamlit_cookies_manager/build/static/js/2.422ca0c4.chunk.js
streamlit_cookies_manager/build/static/js/2.422ca0c4.chunk.js.LICENSE.txt
streamlit_cookies_manager/build/static/js/2.422ca0c4.chunk.js.map
streamlit_cookies_manager/build/static/js/main.f1f38c24.chunk.js
streamlit_cookies_manager/build/static/js/main.f1f38c24.chunk.js.map
streamlit_cookies_manager/build/static/js/runtime-main.9b51049f.js
streamlit_cookies_manager/build/static/js/runtime-main.9b51049f.js.map
streamlit_cookies_manager/package-lock.json
streamlit_cookies_manager/package.json
streamlit_cookies_manager/public/index.html
streamlit_cookies_manager/src/index.ts
streamlit_cookies_manager/src/react-app-env.d.ts
streamlit_cookies_manager/tsconfig.json
streamlit_cookies_manager-0.1.1.dist-info/WHEEL
streamlit_cookies_manager-0.1.1.dist-info/METADATA
streamlit_cookies_manager-0.1.1.dist-info/RECORD
