Metadata-Version: 2.1
Name: streamlit-cookies-manager
Version: 0.1.1
Summary: Access and save cookies from Streamlit
License: Apache-2.0
Author: Tomasz Kontusz
Author-email: tomasz.kontusz@gmail.com
Requires-Python: >=3.9,<4.0
Classifier: License :: OSI Approved :: Apache Software License
Classifier: Programming Language :: Python :: 3
Classifier: Programming Language :: Python :: 3.10
Classifier: Programming Language :: Python :: 3.9
Requires-Dist: streamlit (>0.63)
